README.md
setup.cfg
setup.py
league/__init__.py
league/client.py
league/enums.py
league/errors.py
league/http.py
league/leagues.py
league/mastery.py
league/match.py
league/partial_match.py
league/riotDTO.py
league/spectator.py
league/static_data.py
league/status.py
league/summoner.py
league/tournament.py
league.py.egg-info/PKG-INFO
league.py.egg-info/SOURCES.txt
league.py.egg-info/dependency_links.txt
league.py.egg-info/requires.txt
league.py.egg-info/top_level.txt