Metadata-Version: 1.2
Name: league.py
Version: 0.3.6b0
Summary: An Asyncio friendly wrapper for Riot's League API
Home-page: https://github.com/datmellow/League.py
Author: datmellow
Author-email: lucas@iceteacity.com
License: MIT
Platform: UNKNOWN
Classifier: Development Status :: 3 - Alpha
Classifier: License :: OSI Approved :: MIT License
Classifier: Intended Audience :: Developers
Classifier: Natural Language :: English
Classifier: Operating System :: OS Independent
Classifier: Programming Language :: Python :: 3.5
Classifier: Topic :: Internet
Classifier: Topic :: Software Development :: Libraries
Classifier: Topic :: Software Development :: Libraries :: Python Modules
Classifier: Topic :: Utilities
Requires-Python: >=3.5
